    [
        {
            "maxDistinctCategoryNumber": 5,
            "exactCategoryNumber": 0,
            "repetitionNumber": 6,
            "othersEmpty": false,
            "schema": [
                {
                    "x": 0,
                    "y": 0
                },
                {
                    "x": 0,
                    "y": 1
                }
            ],
            "graphics" : {
                "ascii" : "+---+\n| = |\n|---| x 6\n| = |\n+---+",
                "gui" : "NotAvailable"
            }
        },
        {
            "maxDistinctCategoryNumber": 5,
            "exactCategoryNumber": 0,
            "repetitionNumber": 1,
            "othersEmpty": false,
            "schema": [
                {
                    "x": 0,
                    "y": 0
                },
                {
                    "x": 0,
                    "y": 4
                },
                {
                    "x": 5,
                    "y": 0
                },
                {
                    "x": 5,
                    "y": 4
                }
            ],
            "graphics" : {
            "ascii" : "+---+---+---+---+---+\n| = |   |   |   | = |\n|---|---|---|---|---|\n|   |   |   |   |   |\n|---|---|---|---|---|\n|   |   |   |   |   |\n|---|---|---|---|---|\n|   |   |   |   |   |\n|---|---|---|---|---|\n|   |   |   |   |   |\n|---|---|---|---|---|\n| = |   |   |   | = |\n+---+---+---+---+---+",
            "gui" : "NotAvailable"
            }
        },
        {
            "maxDistinctCategoryNumber": 3,
            "exactCategoryNumber": 0,
            "repetitionNumber": 4,
            "othersEmpty": false,
            "schema": [
                {
                    "x": 0,
                    "y": 0
                },
                {
                    "x": 0,
                    "y": 1
                },
                {
                    "x": 0,
                    "y": 2
                },
                {
                    "x": 0,
                    "y": 3
                }
            ],
            "graphics" : {
            "ascii" : "+---+\n| = |\n|---|\n| = |\n|---| x 4\n| = |\n|---|\n| = |\n+---+",
            "gui" : "NotAvailable"
            }
        },
        {
            "maxDistinctCategoryNumber": 5,
            "exactCategoryNumber": 0,
            "repetitionNumber": 2,
            "othersEmpty": false,
            "schema": [
                {
                    "x": 0,
                    "y": 0
                },
                {
                    "x": 0,
                    "y": 1
                },
                {
                    "x": 1,
                    "y": 0
                },
                {
                    "x": 1,
                    "y": 1
                }
            ],
            "graphics" : {
            "ascii" : "+---+---+\n| = | = |\n|---|---| x 2\n| = | = |\n+---+---+",
            "gui" : "NotAvailable"
            }
        },
        {
            "maxDistinctCategoryNumber": 3,
            "exactCategoryNumber": 0,
            "repetitionNumber": 3,
            "othersEmpty": false,
            "schema": [
                {
                    "x": 0,
                    "y": 0
                },
                {
                    "x": 1,
                    "y": 0
                },
                {
                    "x": 2,
                    "y": 0
                },
                {
                    "x": 3,
                    "y": 0
                },
                {
                    "x": 4,
                    "y": 0
                },
                {
                    "x": 5,
                    "y": 0
                }
            ],
            "graphics" : {
            "ascii" : "+---+\n|   |\n|---|\n|   |\n|---| max 3 !=\n|   |\n|---|\n|   | x 3\n|---|\n|   |\n|---| \n|   |\n+---+",
            "gui" : "NotAvailable"
            }
        },
        {
            "maxDistinctCategoryNumber": 6,
            "exactCategoryNumber": 0,
            "repetitionNumber": 8,
            "othersEmpty": false,
            "schema": [
                {
                    "x": 0,
                    "y": 0
                }
            ],
            "graphics" : {
            "ascii" : "+---+\n| = | x 8\n+---+",
            "gui" : "NotAvailable"
            }
        },
        {
            "maxDistinctCategoryNumber": 6,
            "exactCategoryNumber": 0,
            "repetitionNumber": 3,
            "othersEmpty": false,
            "schema": [
                {
                    "x": 0,
                    "y": 0
                },
                {
                    "x": 1,
                    "y": 1
                },
                {
                    "x": 2,
                    "y": 2
                },
                {
                    "x": 3,
                    "y": 3
                },
                {
                    "x": 4,
                    "y": 4
                }
            ],
            "graphics" : {
                "ascii" : "+---+\n| = |\n+---|---+\n    | = |\n    +---+---+\n        | = |\n        +---|---+\n            | = |\n            +---|---+\n                | = |\n                +---+",
                "gui" : "NotAvailable"
            }
        },
        {
            "maxDistinctCategoryNumber": 3,
            "exactCategoryNumber": 0,
            "repetitionNumber": 4,
            "othersEmpty": false,
            "schema": [
                {
                    "x": 0,
                    "y": 0
                },
                {
                    "x": 0,
                    "y": 1
                },
                {
                    "x": 0,
                    "y": 2
                },
                {
                    "x": 0,
                    "y": 3
                },
                {
                    "x": 0,
                    "y": 4
                }
            ],
            "graphics" : {
                "ascii" : "+---+---+---+---+---+\n| %s| %s| %s| %s| %s|\n+---+---+---+---+---+\n       max 3 !=\n          x4",
                "gui" : "NotAvailable"
            }
        },
        {
            "maxDistinctCategoryNumber": 6,
            "exactCategoryNumber": 6,
            "repetitionNumber": 2,
            "othersEmpty": false,
            "schema": [
                {
                    "x": 0,
                    "y": 0
                },
                {
                    "x": 1,
                    "y": 0
                },
                {
                    "x": 2,
                    "y": 0
                },
                {
                    "x": 3,
                    "y": 0
                },
                {
                    "x": 4,
                    "y": 0
                },
                {
                    "x": 5,
                    "y": 0
                }
            ],
            "graphics" : {
                "ascii" : "+---+\n|=/=|\n|---|\n|=/=|\n|---|\n|=/=|\n|---| x 2\n|=/=|\n|---|\n|=/=|\n|---| \n|=/=|\n+---+",
                "gui" : "NotAvailable"
            }
        },
        {
            "maxDistinctCategoryNumber": 5,
            "exactCategoryNumber": 5,
            "repetitionNumber": 2,
            "othersEmpty": false,
            "schema": [
                {
                    "x": 0,
                    "y": 0
                },
                {
                    "x": 0,
                    "y": 1
                },
                {
                    "x": 0,
                    "y": 2
                },
                {
                    "x": 0,
                    "y": 3
                },
                {
                    "x": 0,
                    "y": 4
                }
            ],
            "graphics" : {
                "ascii" : "+---+---+---+---+---+\n|=/=|=/=|=/=|=/=|=/=|\n+---+---+---+---+---+\n          x3",
                "gui" : "NotAvailable"
            }
        },
        {
            "maxDistinctCategoryNumber": 5,
            "exactCategoryNumber": 0,
            "repetitionNumber": 1,
            "othersEmpty": false,
            "schema": [
                {
                    "x": 0,
                    "y": 0
                },
                {
                    "x": 1,
                    "y": 1
                },
                {
                    "x": 0,
                    "y": 2
                },
                {
                    "x": 2,
                    "y": 0
                },
                {
                    "x": 2,
                    "y": 2
                }
            ],
            "graphics" : {
                "ascii" : "+---+   +---+\n| = |   | = |\n+---+---+---+\n    | = |\n+---+---+---+\n| = |   | = |\n+---+   +---+",
                "gui" : "NotAvailable"
            }
        },
        {
            "maxDistinctCategoryNumber": 6,
            "exactCategoryNumber": 0,
            "repetitionNumber": 1,
            "othersEmpty": true,
            "schema": [
                {
                    "x": 0,
                    "y": 0
                }
            ],
            "graphics" : {
                "ascii" : "+---+\n|   |\n|---|---+\n|   |   |\n|---|---|---+\n|   |   |   |\n|---|---|---|---+\n|   |   |   |   |\n|---|---|---|---|---+\n|   |   |   |   |   |\n+---+---+---+---+---+",
                "gui" : "NotAvailable"
            }
        }
    ]